{
    "response": {
        "code": "200",
        "message": "Consulta realizada con éxito",
        "success": "True"
    },
    "assets": [
        {
            "assetId": 2330,
            "activeFlag": 1,
            "arrears": null,
            "assetDescription": "GRUA\nUSADA MARCA:TEREX MODELO: RT780 NO. DE SERIE 1T9RT600HCW160978 AÑO 2012",
            "partDescription": null,
            "assetName": "GRUA\nUSADA ",
            "brand": "TEREX ",
            "collateralDescription": null,
            "collateralType": null,
            "colour": null,
            "conceptId": 824,
            "createdBy": 223005130,
            "createdOn": 1580234294607,
            "documentId": "0698A000000eMWdQAM",
            "ecPolicy": null,
            "engineNum": null,
            "engineType": null,
            "faCategory": null,
            "faSubcategory": null,
            "fuel": null,
            "importedBy": null,
            "importedOn": null,
            "incisoInsurance": null,
            "insuranceCompany": null,
            "insuranceExpirationDate": null,
            "insurancePolicy": null,
            "keyVehicular": null,
            "model": "RT780 ",
            "modelYear": "2012",
            "modifiedBy": 223005130,
            "modifiedOn": 1580234294607,
            "numberCylinders": null,
            "numberDoors": null,
            "numberPassengers": null,
            "paymentAmount": null,
            "paymentFrecuency": null,
            "paymentOrder": null,
            "paymentType": null,
            "pediment": null,
            "period": null,
            "plates": null,
            "quantity": "1",
            "serialNumber": " 1T9RT600HCW160978 ",
            "softCost": null,
            "takedownId": "a2Y8A000000aHoMUAU",
            "totalCost": 8048100,
            "transmission": null,
            "unitCost": 8048100
        }
    ]
}